{
	"pattrstorage" : 	{
		"name" : "theeffects",
		"slots" : 		{
			"1" : 			{
				"id" : 1,
				"data" : 				{
					"br" : [ 1.0 ],
					"co" : [ 1.0 ],
					"sa" : [ -1.0 ],
					"amp" : [ 0.0 ],
					"freq" : [ 0.0 ],
					"cx" : [ 0.0 ],
					"cy" : [ 0.0 ]
				}

			}
,
			"2" : 			{
				"id" : 2,
				"data" : 				{
					"br" : [ 1.0 ],
					"co" : [ 3.0 ],
					"sa" : [ 0.0 ],
					"amp" : [ 0.0 ],
					"freq" : [ 0.0 ],
					"cx" : [ 0.0 ],
					"cy" : [ 0.0 ]
				}

			}
,
			"3" : 			{
				"id" : 3,
				"data" : 				{
					"br" : [ 1.0 ],
					"co" : [ 1.0 ],
					"sa" : [ 1.0 ],
					"amp" : [ 2.3 ],
					"freq" : [ 0.4 ],
					"cx" : [ 94.0 ],
					"cy" : [ 87.0 ]
				}

			}
,
			"4" : 			{
				"id" : 4,
				"data" : 				{
					"br" : [ 1.0 ],
					"co" : [ 1.0 ],
					"sa" : [ 1.0 ],
					"amp" : [ 17.0 ],
					"freq" : [ 0.12 ],
					"cx" : [ 231.0 ],
					"cy" : [ 469.0 ]
				}

			}
,
			"5" : 			{
				"id" : 5,
				"data" : 				{
					"br" : [ 1.0 ],
					"co" : [ 1.0 ],
					"sa" : [ -1.0 ],
					"amp" : [ 4.0 ],
					"freq" : [ -0.76 ],
					"cx" : [ 231.0 ],
					"cy" : [ 469.0 ]
				}

			}
,
			"6" : 			{
				"id" : 6,
				"data" : 				{
					"br" : [ 1.0 ],
					"co" : [ 1.0 ],
					"sa" : [ -1.0 ],
					"amp" : [ 39.0 ],
					"freq" : [ 3.0 ],
					"cx" : [ 231.0 ],
					"cy" : [ 469.0 ]
				}

			}
,
			"7" : 			{
				"id" : 7,
				"data" : 				{
					"br" : [ 1.0 ],
					"co" : [ 4.0 ],
					"sa" : [ 1.0 ],
					"amp" : [ 39.0 ],
					"freq" : [ 3.0 ],
					"cx" : [ 231.0 ],
					"cy" : [ 469.0 ]
				}

			}
,
			"8" : 			{
				"id" : 8,
				"data" : 				{
					"br" : [ 1.0 ],
					"co" : [ 4.0 ],
					"sa" : [ 1.0 ],
					"amp" : [ 72.0 ],
					"freq" : [ 0.1 ],
					"cx" : [ 514.0 ],
					"cy" : [ 144.0 ]
				}

			}
,
			"9" : 			{
				"id" : 9,
				"data" : 				{
					"br" : [ 1.0 ],
					"co" : [ 4.0 ],
					"sa" : [ 1.0 ],
					"amp" : [ 72.0 ],
					"freq" : [ 0.298 ],
					"cx" : [ 139.0 ],
					"cy" : [ 474.0 ]
				}

			}
,
			"10" : 			{
				"id" : 10,
				"data" : 				{
					"br" : [ 1.0 ],
					"co" : [ 4.0 ],
					"sa" : [ 1.0 ],
					"amp" : [ -111.0 ],
					"freq" : [ 0.782 ],
					"cx" : [ 325.0 ],
					"cy" : [ 474.0 ]
				}

			}

		}

	}

}
